polardb_mysql_mcp_server/__init__.py
polardb_mysql_mcp_server/doc_import.py
polardb_mysql_mcp_server/server.py
polardb_mysql_mcp_server-0.8.0.dist-info/METADATA
polardb_mysql_mcp_server-0.8.0.dist-info/WHEEL
polardb_mysql_mcp_server-0.8.0.dist-info/entry_points.txt
polardb_mysql_mcp_server-0.8.0.dist-info/top_level.txt
polardb_mysql_mcp_server-0.8.0.dist-info/RECORD
