Metadata-Version: 2.4
Name: polardb-mysql-mcp-server
Version: 0.8.0
Summary: MCP server for polardb mysql
Requires-Python: >=3.12
Requires-Dist: mcp[cli]>=1.6.0
Requires-Dist: mysql-connector-python>=9.3.0
Requires-Dist: sqlparse>=0.4.4
Requires-Dist: langchain>=0.3.0
Requires-Dist: langchain-community>=0.3.0
Requires-Dist: mammoth>=1.4.0
